[
  {
    "REG_NAMEpro": "大同區",
    "CASE_LOCATIONpro": "長安西路",
    "CASE_RANGEpro": "",
    "WORK_DATEpro": "~",
    "CTR_WNAMEpro": "",
    "CTR_ONAMEpro": "",
    "CASE_STATUSpro": "2",
    "CASE_TYPEpro": "1",
    "dtResultpro": [
      {
        "KEY": null,
        "P1NAME": null,
        "P2NAME": null,
        "GEO_TYPE": "Polygon",
        "POINTS": [
          {
            "P1": 121.50828941916927,
            "P2": 25.052095705739614
          },
          {
            "P1": 121.50820971253279,
            "P2": 25.051497870881779
          },
          {
            "P1": 121.51211142137716,
            "P2": 25.051695566155221
          },
          {
            "P1": 121.5209863313594,
            "P2": 25.049729645484994
          },
          {
            "P1": 121.52102584304424,
            "P2": 25.049940603478248
          },
          {
            "P1": 121.51191933589472,
            "P2": 25.051942507838991
          },
          {
            "P1": 121.5082114534016,
            "P2": 25.051920058537316
          },
          {
            "P1": 121.50828941916927,
            "P2": 25.052095705739614
          }
        ]
      }
    ]
  }
]