[
  {
    "REG_NAMEpro": "士林區",
    "CASE_LOCATIONpro": "承德路四段一巷23號",
    "CASE_RANGEpro": "承德路四段一巷23號、通河街二巷38-1號、通河街3號、通河街17號、通河街19號、承德路四段10巷11號、承德路四段10巷15號、承德路四段10巷64號",
    "WORK_DATEpro": "98/10/09~98/11/09",
    "CTR_WNAMEpro": "",
    "CTR_ONAMEpro": "",
    "CASE_STATUSpro": "6",
    "CASE_TYPEpro": "3",
    "dtResultpro": [
      {
        "KEY": null,
        "P1NAME": null,
        "P2NAME": null,
        "GEO_TYPE": "LineString",
        "POINTS": [
          {
            "P1": 121.52207132140319,
            "P2": 25.077958140757676
          },
          {
            "P1": 121.52212311908477,
            "P2": 25.077926428103414
          }
        ]
      },
      {
        "KEY": null,
        "P1NAME": null,
        "P2NAME": null,
        "GEO_TYPE": "LineString",
        "POINTS": [
          {
            "P1": 121.52257018377742,
            "P2": 25.077671087472325
          },
          {
            "P1": 121.522596943056,
            "P2": 25.077721444369761
          }
        ]
      },
      {
        "KEY": null,
        "P1NAME": null,
        "P2NAME": null,
        "GEO_TYPE": "LineString",
        "POINTS": [
          {
            "P1": 121.52108996788572,
            "P2": 25.07951406030918
          },
          {
            "P1": 121.52120091415394,
            "P2": 25.079463051205945
          }
        ]
      },
      {
        "KEY": null,
        "P1NAME": null,
        "P2NAME": null,
        "GEO_TYPE": "LineString",
        "POINTS": [
          {
            "P1": 121.52088073083736,
            "P2": 25.079606683383744
          },
          {
            "P1": 121.52091429988886,
            "P2": 25.079591250743217
          }
        ]
      },
      {
        "KEY": null,
        "P1NAME": null,
        "P2NAME": null,
        "GEO_TYPE": "LineString",
        "POINTS": [
          {
            "P1": 121.51948937823575,
            "P2": 25.080126135698453
          },
          {
            "P1": 121.5195510591971,
            "P2": 25.08009777905939
          }
        ]
      },
      {
        "KEY": null,
        "P1NAME": null,
        "P2NAME": null,
        "GEO_TYPE": "LineString",
        "POINTS": [
          {
            "P1": 121.52329737818155,
            "P2": 25.079797043394617
          },
          {
            "P1": 121.52331970845728,
            "P2": 25.079789326470031
          }
        ]
      },
      {
        "KEY": null,
        "P1NAME": null,
        "P2NAME": null,
        "GEO_TYPE": "LineString",
        "POINTS": [
          {
            "P1": 121.52334819656238,
            "P2": 25.079785407383305
          },
          {
            "P1": 121.52336636292139,
            "P2": 25.079784070287932
          }
        ]
      },
      {
        "KEY": null,
        "P1NAME": null,
        "P2NAME": null,
        "GEO_TYPE": "LineString",
        "POINTS": [
          {
            "P1": 121.52354471061443,
            "P2": 25.079749069046489
          },
          {
            "P1": 121.52364809770279,
            "P2": 25.079737247008037
          }
        ]
      }
    ]
  }
]