[
  {
    "REG_NAMEpro": "中正區",
    "CASE_LOCATIONpro": "思源街與汀州路3段口",
    "CASE_RANGEpro": "思源街與汀州路3段口",
    "WORK_DATEpro": "99/04/08~99/04/27",
    "CTR_WNAMEpro": "",
    "CTR_ONAMEpro": "",
    "CASE_STATUSpro": "6",
    "CASE_TYPEpro": "3",
    "dtResultpro": [
      {
        "KEY": null,
        "P1NAME": null,
        "P2NAME": null,
        "GEO_TYPE": "LineString",
        "POINTS": [
          {
            "P1": 121.53204471060906,
            "P2": 25.014601249099034
          },
          {
            "P1": 121.53206196134116,
            "P2": 25.014616841553497
          },
          {
            "P1": 121.53206884190675,
            "P2": 25.014618690081843
          },
          {
            "P1": 121.53207777683113,
            "P2": 25.014619289925555
          },
          {
            "P1": 121.53208944181976,
            "P2": 25.014615487015007
          },
          {
            "P1": 121.5321010893252,
            "P2": 25.014606681667139
          },
          {
            "P1": 121.53211067703826,
            "P2": 25.014599756838695
          }
        ]
      }
    ]
  }
]