[
  {
    "REG_NAMEpro": "中山區",
    "CASE_LOCATIONpro": "林森南路ˋ公園路、承德路4段、環河北路、民權西路",
    "CASE_RANGEpro": "林森南路43號前\r\n公園路11巷巷口前\r\n承德路4段235號前\r\n環河北路439號前\r\n民權西路112號前",
    "WORK_DATEpro": "100/06/01~100/06/30",
    "CTR_WNAMEpro": "",
    "CTR_ONAMEpro": "",
    "CASE_STATUSpro": "2",
    "CASE_TYPEpro": "2",
    "dtResultpro": [
      {
        "KEY": null,
        "P1NAME": null,
        "P2NAME": null,
        "GEO_TYPE": "Point",
        "POINTS": [
          {
            "P1": 121.51704117571983,
            "P2": 25.062573859820414
          }
        ]
      },
      {
        "KEY": null,
        "P1NAME": null,
        "P2NAME": null,
        "GEO_TYPE": "Point",
        "POINTS": [
          {
            "P1": 121.50871087759914,
            "P2": 25.062286823652531
          }
        ]
      },
      {
        "KEY": null,
        "P1NAME": null,
        "P2NAME": null,
        "GEO_TYPE": "Point",
        "POINTS": [
          {
            "P1": 121.52208568982394,
            "P2": 25.087923713898181
          }
        ]
      },
      {
        "KEY": null,
        "P1NAME": null,
        "P2NAME": null,
        "GEO_TYPE": "Point",
        "POINTS": [
          {
            "P1": 121.51741328566706,
            "P2": 25.045860663116358
          }
        ]
      },
      {
        "KEY": null,
        "P1NAME": null,
        "P2NAME": null,
        "GEO_TYPE": "Point",
        "POINTS": [
          {
            "P1": 121.52208822339019,
            "P2": 25.040139977945486
          }
        ]
      }
    ]
  }
]