[
  {
    "REG_NAMEpro": "內湖區",
    "CASE_LOCATIONpro": "五分街、五分街14巷及康寧路3段245巷路面更新工程",
    "CASE_RANGEpro": "五分街、五分街14巷及康寧路3段245巷",
    "WORK_DATEpro": "101/12/24~102/01/22",
    "CTR_WNAMEpro": "磐峰營造有限公司",
    "CTR_ONAMEpro": "永健工程顧問有限公司",
    "CASE_STATUSpro": "6",
    "CASE_TYPEpro": "2",
    "dtResultpro": [
      {
        "KEY": null,
        "P1NAME": null,
        "P2NAME": null,
        "GEO_TYPE": "Polygon",
        "POINTS": [
          {
            "P1": 121.6119236508128,
            "P2": 25.067523210280108
          },
          {
            "P1": 121.61186021310657,
            "P2": 25.067423148758216
          },
          {
            "P1": 121.61188647339739,
            "P2": 25.067430206453672
          },
          {
            "P1": 121.61362679288445,
            "P2": 25.067222377383118
          },
          {
            "P1": 121.61376838212226,
            "P2": 25.067217014799127
          },
          {
            "P1": 121.61378450973143,
            "P2": 25.067295773313415
          },
          {
            "P1": 121.61369278295453,
            "P2": 25.067308095729093
          },
          {
            "P1": 121.61255265178447,
            "P2": 25.067441791082764
          },
          {
            "P1": 121.61253702388821,
            "P2": 25.067463353346305
          },
          {
            "P1": 121.61247935331645,
            "P2": 25.067468368569191
          },
          {
            "P1": 121.61245569169864,
            "P2": 25.067456522973359
          },
          {
            "P1": 121.61194983991791,
            "P2": 25.067515936401747
          },
          {
            "P1": 121.6119236508128,
            "P2": 25.067523210280108
          }
        ]
      },
      {
        "KEY": null,
        "P1NAME": null,
        "P2NAME": null,
        "GEO_TYPE": "Polygon",
        "POINTS": [
          {
            "P1": 121.61364065305554,
            "P2": 25.067224884361856
          },
          {
            "P1": 121.61365879346921,
            "P2": 25.067185843100489
          },
          {
            "P1": 121.61348665076852,
            "P2": 25.066368262643348
          },
          {
            "P1": 121.6133359354848,
            "P2": 25.066171270631408
          },
          {
            "P1": 121.61330529498508,
            "P2": 25.066154697374333
          },
          {
            "P1": 121.61340889885283,
            "P2": 25.066095819920623
          },
          {
            "P1": 121.61340292600021,
            "P2": 25.066123677660119
          },
          {
            "P1": 121.61354436319847,
            "P2": 25.066298441499313
          },
          {
            "P1": 121.6135749344387,
            "P2": 25.066301098461857
          },
          {
            "P1": 121.61358743470224,
            "P2": 25.066356712918832
          },
          {
            "P1": 121.61356616931609,
            "P2": 25.066381850559257
          },
          {
            "P1": 121.61362571209625,
            "P2": 25.066679418197332
          },
          {
            "P1": 121.61364719939532,
            "P2": 25.066698812524219
          },
          {
            "P1": 121.61365961652962,
            "P2": 25.066737727479904
          },
          {
            "P1": 121.61364132364054,
            "P2": 25.066746153009884
          },
          {
            "P1": 121.61373518745633,
            "P2": 25.067185527304385
          },
          {
            "P1": 121.61375061882242,
            "P2": 25.06721607987058
          },
          {
            "P1": 121.61364065305554,
            "P2": 25.067224884361856
          }
        ]
      },
      {
        "KEY": null,
        "P1NAME": null,
        "P2NAME": null,
        "GEO_TYPE": "Polygon",
        "POINTS": [
          {
            "P1": 121.61141027178587,
            "P2": 25.066683879473707
          },
          {
            "P1": 121.6114748570447,
            "P2": 25.066767112672327
          },
          {
            "P1": 121.61152061038445,
            "P2": 25.066750224379938
          },
          {
            "P1": 121.61229364586349,
            "P2": 25.066733121649303
          },
          {
            "P1": 121.61283300389712,
            "P2": 25.06642751584176
          },
          {
            "P1": 121.6136709890351,
            "P2": 25.065953675670649
          },
          {
            "P1": 121.61350571626294,
            "P2": 25.065901475911037
          },
          {
            "P1": 121.61350589648892,
            "P2": 25.065937658145259
          },
          {
            "P1": 121.61279294691623,
            "P2": 25.066360881837117
          },
          {
            "P1": 121.61273177673992,
            "P2": 25.066350001085695
          },
          {
            "P1": 121.61268306489932,
            "P2": 25.066386385101563
          },
          {
            "P1": 121.61267713340564,
            "P2": 25.06642259256105
          },
          {
            "P1": 121.61226272863888,
            "P2": 25.06666088319405
          },
          {
            "P1": 121.61144695458344,
            "P2": 25.066686511704162
          },
          {
            "P1": 121.61141027178587,
            "P2": 25.066683879473707
          }
        ]
      },
      {
        "KEY": null,
        "P1NAME": null,
        "P2NAME": null,
        "GEO_TYPE": "Polygon",
        "POINTS": [
          {
            "P1": 121.61366836477173,
            "P2": 25.065864975323173
          },
          {
            "P1": 121.61397606870605,
            "P2": 25.065671702609372
          },
          {
            "P1": 121.6140966925275,
            "P2": 25.065705489530242
          },
          {
            "P1": 121.61376272501147,
            "P2": 25.06591601397378
          },
          {
            "P1": 121.61363084275146,
            "P2": 25.065889130479238
          },
          {
            "P1": 121.61366836477173,
            "P2": 25.065864975323173
          }
        ]
      }
    ]
  }
]