[
  {
    "REG_NAMEpro": "內湖區",
    "CASE_LOCATIONpro": "永保街",
    "CASE_RANGEpro": "安康路288號至安康路51號",
    "WORK_DATEpro": "101/11/27~101/12/10",
    "CTR_WNAMEpro": "興成營造有限公司",
    "CTR_ONAMEpro": "世偉工程顧問有限公司",
    "CASE_STATUSpro": "6",
    "CASE_TYPEpro": "2",
    "dtResultpro": [
      {
        "KEY": null,
        "P1NAME": null,
        "P2NAME": null,
        "GEO_TYPE": "Polygon",
        "POINTS": [
          {
            "P1": 121.59579313445995,
            "P2": 25.062748647278621
          },
          {
            "P1": 121.59634967736567,
            "P2": 25.062904870363027
          },
          {
            "P1": 121.59686760488661,
            "P2": 25.063018030937982
          },
          {
            "P1": 121.59727459022238,
            "P2": 25.063082246722413
          },
          {
            "P1": 121.59728095890137,
            "P2": 25.062997847723793
          },
          {
            "P1": 121.59673825907862,
            "P2": 25.062901251257525
          },
          {
            "P1": 121.59614113883541,
            "P2": 25.0627637135495
          },
          {
            "P1": 121.59581974781209,
            "P2": 25.062645646099124
          },
          {
            "P1": 121.59579313445995,
            "P2": 25.062748647278621
          }
        ]
      },
      {
        "KEY": null,
        "P1NAME": null,
        "P2NAME": null,
        "GEO_TYPE": "Polygon",
        "POINTS": [
          {
            "P1": 121.5972696567873,
            "P2": 25.063081379489454
          },
          {
            "P1": 121.59895114185541,
            "P2": 25.063319662311706
          },
          {
            "P1": 121.59895310465035,
            "P2": 25.063237968942545
          },
          {
            "P1": 121.59726926073537,
            "P2": 25.062999695613531
          },
          {
            "P1": 121.5972669111964,
            "P2": 25.0630018546821
          },
          {
            "P1": 121.5972696567873,
            "P2": 25.063081379489454
          }
        ]
      },
      {
        "KEY": null,
        "P1NAME": null,
        "P2NAME": null,
        "GEO_TYPE": "Polygon",
        "POINTS": [
          {
            "P1": 121.59891358303544,
            "P2": 25.063316659465329
          },
          {
            "P1": 121.60252007497489,
            "P2": 25.063799741465157
          },
          {
            "P1": 121.60252448460444,
            "P2": 25.063676446661475
          },
          {
            "P1": 121.60069372348774,
            "P2": 25.063446442545597
          },
          {
            "P1": 121.59892314205857,
            "P2": 25.063220738819446
          },
          {
            "P1": 121.59891815166134,
            "P2": 25.06322532476257
          },
          {
            "P1": 121.59891358303544,
            "P2": 25.063316659465329
          }
        ]
      },
      {
        "KEY": null,
        "P1NAME": null,
        "P2NAME": null,
        "GEO_TYPE": "Polygon",
        "POINTS": [
          {
            "P1": 121.60249063218473,
            "P2": 25.0638126070451
          },
          {
            "P1": 121.60687923031767,
            "P2": 25.06437229855235
          },
          {
            "P1": 121.60690102937777,
            "P2": 25.064200315156224
          },
          {
            "P1": 121.60248995959094,
            "P2": 25.063675094260255
          },
          {
            "P1": 121.60249063218473,
            "P2": 25.0638126070451
          }
        ]
      }
    ]
  }
]